psyleague
