Metadata-Version: 2.1
Name: psyleague
Version: 0.4.1
Summary: Local league system for bot contests.
Home-page: https://github.com/FakePsyho/psyleague
Author: Psyho
License: MIT
Keywords: CompetitiveProgramming,CodinGame,Tester
Platform: UNKNOWN
Classifier: Development Status :: 3 - Alpha
Classifier: Intended Audience :: Developers
Classifier: Topic :: Scientific/Engineering
Classifier: Environment :: Console
Classifier: License :: OSI Approved :: MIT License
Classifier: Operating System :: OS Independent
Classifier: Programming Language :: Python :: 3
License-File: LICENSE
